<?xml version="1.0" encoding="UTF-8"?>
<tv>
  <channel id="Canal 2">
    <display-name>Canal 2</display-name>
  </channel>
  <channel id="TV Câmara">
    <display-name>TV Câmara</display-name>
  </channel>
  <channel id="TV Brasil">
    <display-name>TV Brasil</display-name>
  </channel>
  <channel id="TV Brasil 2">
    <display-name>TV Brasil 2</display-name>
  </channel>
  <channel id="TV Justiça">
    <display-name>TV Justiça</display-name>
  </channel>
  <channel id="Canal Legislativo">
    <display-name>Canal Legislativo</display-name>
  </channel>
  <channel id="TV Escola">
    <display-name>TV Escola</display-name>
  </channel>
  <channel id="Canal Comunitário">
    <display-name>Canal Comunitário</display-name>
  </channel>
  <channel id="TV Senado">
    <display-name>TV Senado</display-name>
  </channel>
  <channel id="Canal Universitário">
    <display-name>Canal Universitário</display-name>
  </channel>
  <channel id="RIT TV">
    <display-name>RIT TV</display-name>
  </channel>
  <channel id="TV Pai Eterno">
    <display-name>TV Pai Eterno</display-name>
  </channel>
  <channel id="Cultura">
    <display-name>Cultura</display-name>
  </channel>
  <channel id="SBT">
    <display-name>SBT</display-name>
  </channel>
  <channel id="Globo">
    <display-name>Globo</display-name>
  </channel>
  <channel id="Record">
    <display-name>Record</display-name>
  </channel>
  <channel id="Rede TV">
    <display-name>Rede TV</display-name>
  </channel>
  <channel id="Gazeta">
    <display-name>Gazeta</display-name>
  </channel>
  <channel id="Band">
    <display-name>Band</display-name>
  </channel>
  <channel id="Mega TV">
    <display-name>Mega TV</display-name>
  </channel>
  <channel id="Rede 21">
    <display-name>Rede 21</display-name>
  </channel>
  <channel id="Rede Gospel">
    <display-name>Rede Gospel</display-name>
  </channel>
  <channel id="Polishop">
    <display-name>Polishop</display-name>
  </channel>
  <channel id="Shoptime">
    <display-name>Shoptime</display-name>
  </channel>
  <channel id="Canal do cliente">
    <display-name>Canal do cliente</display-name>
  </channel>
  <channel id="Futura">
    <display-name>Futura</display-name>
  </channel>
  <channel id="Off">
    <display-name>Off</display-name>
  </channel>
  <channel id="SporTV 3">
    <display-name>SporTV 3</display-name>
  </channel>
  <channel id="SporTV 2">
    <display-name>SporTV 2</display-name>
  </channel>
  <channel id="SporTV">
    <display-name>SporTV</display-name>
  </channel>
  <channel id="GloboNews">
    <display-name>GloboNews</display-name>
  </channel>
  <channel id="GNT">
    <display-name>GNT</display-name>
  </channel>
  <channel id="Multishow">
    <display-name>Multishow</display-name>
  </channel>
  <channel id="Viva">
    <display-name>Viva</display-name>
  </channel>
  <channel id="Modo viagem">
    <display-name>Modo viagem</display-name>
  </channel>
  <channel id="E">
    <display-name>E</display-name>
  </channel>
  <channel id="TLC">
    <display-name>TLC</display-name>
  </channel>
  <channel id="Arte 1">
    <display-name>Arte 1</display-name>
  </channel>
  <channel id="Food Network">
    <display-name>Food Network</display-name>
  </channel>
  <channel id="Discovery Home  Health">
    <display-name>Discovery Home  Health</display-name>
  </channel>
  <channel id="Curta">
    <display-name>Curta</display-name>
  </channel>
  <channel id="FISH TV">
    <display-name>FISH TV</display-name>
  </channel>
  <channel id="HGTV">
    <display-name>HGTV</display-name>
  </channel>
  <channel id="Woohoo">
    <display-name>Woohoo</display-name>
  </channel>
  <channel id="ESPN">
    <display-name>ESPN</display-name>
  </channel>
  <channel id="ESPN 2">
    <display-name>ESPN 2</display-name>
  </channel>
  <channel id="Espn 4">
    <display-name>Espn 4</display-name>
  </channel>
  <channel id="Band Sports">
    <display-name>Band Sports</display-name>
  </channel>
  <channel id="CNN Brasil">
    <display-name>CNN Brasil</display-name>
  </channel>
  <channel id="Record News">
    <display-name>Record News</display-name>
  </channel>
  <channel id="Band News">
    <display-name>Band News</display-name>
  </channel>
  <channel id="National Geographic">
    <display-name>National Geographic</display-name>
  </channel>
  <channel id="Discovery Channel">
    <display-name>Discovery Channel</display-name>
  </channel>
  <channel id="Animal Planet">
    <display-name>Animal Planet</display-name>
  </channel>
  <channel id="The History Channel">
    <display-name>The History Channel</display-name>
  </channel>
  <channel id="Discovery Turbo">
    <display-name>Discovery Turbo</display-name>
  </channel>
  <channel id="Discovery Science">
    <display-name>Discovery Science</display-name>
  </channel>
  <channel id="Gloobinho">
    <display-name>Gloobinho</display-name>
  </channel>
  <channel id="Discovery Kids">
    <display-name>Discovery Kids</display-name>
  </channel>
  <channel id="Gloob">
    <display-name>Gloob</display-name>
  </channel>
  <channel id="Disney Channel">
    <display-name>Disney Channel</display-name>
  </channel>
  <channel id="Nickelodeon">
    <display-name>Nickelodeon</display-name>
  </channel>
  <channel id="Cartoon Network">
    <display-name>Cartoon Network</display-name>
  </channel>
  <channel id="Nick Jr.">
    <display-name>Nick Jr.</display-name>
  </channel>
  <channel id="cartoonito">
    <display-name>cartoonito</display-name>
  </channel>
  <channel id="TV Rá Tim Bum">
    <display-name>TV Rá Tim Bum</display-name>
  </channel>
  <channel id="Baby Tv">
    <display-name>Baby Tv</display-name>
  </channel>
  <channel id="ZooMoo">
    <display-name>ZooMoo</display-name>
  </channel>
  <channel id="BIS">
    <display-name>BIS</display-name>
  </channel>
  <channel id="MTV">
    <display-name>MTV</display-name>
  </channel>
  <channel id="Play TV">
    <display-name>Play TV</display-name>
  </channel>
  <channel id="Music Box Brazil">
    <display-name>Music Box Brazil</display-name>
  </channel>
  <channel id="Universal TV">
    <display-name>Universal TV</display-name>
  </channel>
  <channel id="Star Channel">
    <display-name>Star Channel</display-name>
  </channel>
  <channel id="Warner Channel">
    <display-name>Warner Channel</display-name>
  </channel>
  <channel id="Sony">
    <display-name>Sony</display-name>
  </channel>
  <channel id="FX">
    <display-name>FX</display-name>
  </channel>
  <channel id="AXN">
    <display-name>AXN</display-name>
  </channel>
  <channel id="Tnt novelas">
    <display-name>Tnt novelas</display-name>
  </channel>
  <channel id="Comedy Central">
    <display-name>Comedy Central</display-name>
  </channel>
  <channel id="AE">
    <display-name>AE</display-name>
  </channel>
  <channel id="ID">
    <display-name>ID</display-name>
  </channel>
  <channel id="Syfy">
    <display-name>Syfy</display-name>
  </channel>
  <channel id="Lifetime">
    <display-name>Lifetime</display-name>
  </channel>
  <channel id="Cinecanal">
    <display-name>Cinecanal</display-name>
  </channel>
  <channel id="AMC">
    <display-name>AMC</display-name>
  </channel>
  <channel id="FilmArts">
    <display-name>FilmArts</display-name>
  </channel>
  <channel id="Canal Brasil">
    <display-name>Canal Brasil</display-name>
  </channel>
  <channel id="TNT">
    <display-name>TNT</display-name>
  </channel>
  <channel id="Megapix">
    <display-name>Megapix</display-name>
  </channel>
  <channel id="Space">
    <display-name>Space</display-name>
  </channel>
  <channel id="Cinemax">
    <display-name>Cinemax</display-name>
  </channel>
  <channel id="Prime Box Brazil">
    <display-name>Prime Box Brazil</display-name>
  </channel>
  <channel id="Studio Universal">
    <display-name>Studio Universal</display-name>
  </channel>
  <channel id="Paramount Network">
    <display-name>Paramount Network</display-name>
  </channel>
  <channel id="TCM">
    <display-name>TCM</display-name>
  </channel>
  <channel id="Telecine Premium">
    <display-name>Telecine Premium</display-name>
  </channel>
  <channel id="Telecine Action">
    <display-name>Telecine Action</display-name>
  </channel>
  <channel id="Telecine Touch">
    <display-name>Telecine Touch</display-name>
  </channel>
  <channel id="Telecine Fun">
    <display-name>Telecine Fun</display-name>
  </channel>
  <channel id="Telecine Pipoca">
    <display-name>Telecine Pipoca</display-name>
  </channel>
  <channel id="Telecine Cult">
    <display-name>Telecine Cult</display-name>
  </channel>
  <channel id="HBO">
    <display-name>HBO</display-name>
  </channel>
  <channel id="HBO 2">
    <display-name>HBO 2</display-name>
  </channel>
  <channel id="HBO +">
    <display-name>HBO +</display-name>
  </channel>
  <channel id="HBO Family">
    <display-name>HBO Family</display-name>
  </channel>
  <channel id="HBO Signature">
    <display-name>HBO Signature</display-name>
  </channel>
  <channel id="Hbo Pop">
    <display-name>Hbo Pop</display-name>
  </channel>
  <channel id="Hbo Mundi">
    <display-name>Hbo Mundi</display-name>
  </channel>
  <channel id="HBO Xtreme">
    <display-name>HBO Xtreme</display-name>
  </channel>
  <channel id="Terra Viva">
    <display-name>Terra Viva</display-name>
  </channel>
  <channel id="Canal Rural">
    <display-name>Canal Rural</display-name>
  </channel>
  <channel id="Agro Mais">
    <display-name>Agro Mais</display-name>
  </channel>
  <channel id="Canal do Boi">
    <display-name>Canal do Boi</display-name>
  </channel>
  <channel id="Rede Vida">
    <display-name>Rede Vida</display-name>
  </channel>
  <channel id="Tv Aparecida">
    <display-name>Tv Aparecida</display-name>
  </channel>
  <channel id="Boa Vontade TV">
    <display-name>Boa Vontade TV</display-name>
  </channel>
  <channel id="CGTN">
    <display-name>CGTN</display-name>
  </channel>
  <channel id="CNN International">
    <display-name>CNN International</display-name>
  </channel>
  <channel id="Bloomberg TV">
    <display-name>Bloomberg TV</display-name>
  </channel>
  <channel id="BBC World News">
    <display-name>BBC World News</display-name>
  </channel>
  <channel id="RAI International">
    <display-name>RAI International</display-name>
  </channel>
  <channel id="TV5 Monde">
    <display-name>TV5 Monde</display-name>
  </channel>
  <channel id="TVE International">
    <display-name>TVE International</display-name>
  </channel>
  <channel id="DW-TV">
    <display-name>DW-TV</display-name>
  </channel>
  <channel id="NHK World Premium">
    <display-name>NHK World Premium</display-name>
  </channel>
  <channel id="SIC International">
    <display-name>SIC International</display-name>
  </channel>
  <channel id="TV Korea">
    <display-name>TV Korea</display-name>
  </channel>
  <channel id="France 24">
    <display-name>France 24</display-name>
  </channel>
  <channel id="Portal do Futebol">
    <display-name>Portal do Futebol</display-name>
  </channel>
  <channel id="Premiere Clubes">
    <display-name>Premiere Clubes</display-name>
  </channel>
  <channel id="Premiere 2">
    <display-name>Premiere 2</display-name>
  </channel>
  <channel id="Premiere 3">
    <display-name>Premiere 3</display-name>
  </channel>
  <channel id="Premiere 4">
    <display-name>Premiere 4</display-name>
  </channel>
  <channel id="Premiere 5">
    <display-name>Premiere 5</display-name>
  </channel>
  <channel id="Premiere 6">
    <display-name>Premiere 6</display-name>
  </channel>
  <channel id="Premiere 7">
    <display-name>Premiere 7</display-name>
  </channel>
  <channel id="Mosaico Multijogos">
    <display-name>Mosaico Multijogos</display-name>
  </channel>
  <channel id="Combate">
    <display-name>Combate</display-name>
  </channel>
  <channel id="Canal de Vendas NET">
    <display-name>Canal de Vendas NET</display-name>
  </channel>
  <channel id="TV Climatempo">
    <display-name>TV Climatempo</display-name>
  </channel>
  <channel id="Jogos Interativos Cartoon">
    <display-name>Jogos Interativos Cartoon</display-name>
  </channel>
  <channel id="Playboy TV">
    <display-name>Playboy TV</display-name>
  </channel>
  <channel id="Sextreme">
    <display-name>Sextreme</display-name>
  </channel>
  <channel id="Venus">
    <display-name>Venus</display-name>
  </channel>
  <channel id="Sexy Hot">
    <display-name>Sexy Hot</display-name>
  </channel>
  <channel id="Música">
    <display-name>Música</display-name>
  </channel>
  <channel id="CANAL DO CLIENTE HD">
    <display-name>CANAL DO CLIENTE HD</display-name>
  </channel>
  <channel id="Globo HD">
    <display-name>Globo HD</display-name>
  </channel>
  <channel id="Band HD">
    <display-name>Band HD</display-name>
  </channel>
  <channel id="Rede TV HD">
    <display-name>Rede TV HD</display-name>
  </channel>
  <channel id="SBT HD">
    <display-name>SBT HD</display-name>
  </channel>
  <channel id="Cultura HD">
    <display-name>Cultura HD</display-name>
  </channel>
  <channel id="Record HD">
    <display-name>Record HD</display-name>
  </channel>
  <channel id="Gazeta HD">
    <display-name>Gazeta HD</display-name>
  </channel>
  <channel id="Mega TV HD">
    <display-name>Mega TV HD</display-name>
  </channel>
  <channel id="Rede Gospel HD">
    <display-name>Rede Gospel HD</display-name>
  </channel>
  <channel id="Polishop TV">
    <display-name>Polishop TV</display-name>
  </channel>
  <channel id="Shoptime TV">
    <display-name>Shoptime TV</display-name>
  </channel>
  <channel id="LIKE HD">
    <display-name>LIKE HD</display-name>
  </channel>
  <channel id="TV Brasil HD">
    <display-name>TV Brasil HD</display-name>
  </channel>
  <channel id="Futura HD">
    <display-name>Futura HD</display-name>
  </channel>
  <channel id="Off HD ³">
    <display-name>Off HD ³</display-name>
  </channel>
  <channel id="SporTV 3 HD ³">
    <display-name>SporTV 3 HD ³</display-name>
  </channel>
  <channel id="SporTV 2 HD ³">
    <display-name>SporTV 2 HD ³</display-name>
  </channel>
  <channel id="SporTV HD ³">
    <display-name>SporTV HD ³</display-name>
  </channel>
  <channel id="GloboNews HD ³">
    <display-name>GloboNews HD ³</display-name>
  </channel>
  <channel id="GNT HD ³">
    <display-name>GNT HD ³</display-name>
  </channel>
  <channel id="Multishow HD ³">
    <display-name>Multishow HD ³</display-name>
  </channel>
  <channel id="Viva HD">
    <display-name>Viva HD</display-name>
  </channel>
  <channel id="Modo viagem HD">
    <display-name>Modo viagem HD</display-name>
  </channel>
  <channel id="E HD">
    <display-name>E HD</display-name>
  </channel>
  <channel id="Fashion TV HD">
    <display-name>Fashion TV HD</display-name>
  </channel>
  <channel id="TLC HD ³">
    <display-name>TLC HD ³</display-name>
  </channel>
  <channel id="Arte 1 HD">
    <display-name>Arte 1 HD</display-name>
  </channel>
  <channel id="FOOD NETWORK HD">
    <display-name>FOOD NETWORK HD</display-name>
  </channel>
  <channel id="Discovery Home  Health HD ³">
    <display-name>Discovery Home  Health HD ³</display-name>
  </channel>
  <channel id="Curta HD">
    <display-name>Curta HD</display-name>
  </channel>
  <channel id="Travel Box Brasil HD">
    <display-name>Travel Box Brasil HD</display-name>
  </channel>
  <channel id="FISH TV HD">
    <display-name>FISH TV HD</display-name>
  </channel>
  <channel id="DogTV HD">
    <display-name>DogTV HD</display-name>
  </channel>
  <channel id="HGTV HD">
    <display-name>HGTV HD</display-name>
  </channel>
  <channel id="Sabor  Arte HD">
    <display-name>Sabor  Arte HD</display-name>
  </channel>
  <channel id="Woohoo HD">
    <display-name>Woohoo HD</display-name>
  </channel>
  <channel id="ESPN 5 HD">
    <display-name>ESPN 5 HD</display-name>
  </channel>
  <channel id="ESPN HD ³">
    <display-name>ESPN HD ³</display-name>
  </channel>
  <channel id="ESPN 2 HD">
    <display-name>ESPN 2 HD</display-name>
  </channel>
  <channel id="ESPN 3 HD">
    <display-name>ESPN 3 HD</display-name>
  </channel>
  <channel id="ESPN 4 HD">
    <display-name>ESPN 4 HD</display-name>
  </channel>
  <channel id="ESPN 6 HD">
    <display-name>ESPN 6 HD</display-name>
  </channel>
  <channel id="Band Sports HD ³">
    <display-name>Band Sports HD ³</display-name>
  </channel>
  <channel id="JP News HD">
    <display-name>JP News HD</display-name>
  </channel>
  <channel id="CNN Brasil HD">
    <display-name>CNN Brasil HD</display-name>
  </channel>
  <channel id="Band News HD">
    <display-name>Band News HD</display-name>
  </channel>
  <channel id="National Geographic HD ³">
    <display-name>National Geographic HD ³</display-name>
  </channel>
  <channel id="Discovery HD ³">
    <display-name>Discovery HD ³</display-name>
  </channel>
  <channel id="Animal Planet HD">
    <display-name>Animal Planet HD</display-name>
  </channel>
  <channel id="History Hd">
    <display-name>History Hd</display-name>
  </channel>
  <channel id="Discovery Turbo HD ³">
    <display-name>Discovery Turbo HD ³</display-name>
  </channel>
  <channel id="Discovery Science HD ³">
    <display-name>Discovery Science HD ³</display-name>
  </channel>
  <channel id="Discovery Theater HD ³">
    <display-name>Discovery Theater HD ³</display-name>
  </channel>
  <channel id="Discovery world HD ³">
    <display-name>Discovery world HD ³</display-name>
  </channel>
  <channel id="History 2 HD">
    <display-name>History 2 HD</display-name>
  </channel>
  <channel id="Gloobinho HD">
    <display-name>Gloobinho HD</display-name>
  </channel>
  <channel id="Discovery Kids HD ³">
    <display-name>Discovery Kids HD ³</display-name>
  </channel>
  <channel id="Gloob HD ³">
    <display-name>Gloob HD ³</display-name>
  </channel>
  <channel id="Disney Channel HD ³">
    <display-name>Disney Channel HD ³</display-name>
  </channel>
  <channel id="Nickelodeon HD">
    <display-name>Nickelodeon HD</display-name>
  </channel>
  <channel id="Cartoon Network HD">
    <display-name>Cartoon Network HD</display-name>
  </channel>
  <channel id="Nick Jr HD ³">
    <display-name>Nick Jr HD ³</display-name>
  </channel>
  <channel id="Cartoonito HD">
    <display-name>Cartoonito HD</display-name>
  </channel>
  <channel id="TV Rá Tim Bum HD ³">
    <display-name>TV Rá Tim Bum HD ³</display-name>
  </channel>
  <channel id="ZooMoo HD">
    <display-name>ZooMoo HD</display-name>
  </channel>
  <channel id="BIS HD ³">
    <display-name>BIS HD ³</display-name>
  </channel>
  <channel id="MTV HD ³">
    <display-name>MTV HD ³</display-name>
  </channel>
  <channel id="Music Box Brazil HD ³">
    <display-name>Music Box Brazil HD ³</display-name>
  </channel>
  <channel id="Trace Brazuca HD">
    <display-name>Trace Brazuca HD</display-name>
  </channel>
  <channel id="MTV Live HD">
    <display-name>MTV Live HD</display-name>
  </channel>
  <channel id="Universal TV HD">
    <display-name>Universal TV HD</display-name>
  </channel>
  <channel id="STAR CHANNEL HD">
    <display-name>STAR CHANNEL HD</display-name>
  </channel>
  <channel id="Warner Channel HD">
    <display-name>Warner Channel HD</display-name>
  </channel>
  <channel id="Sony HD ³">
    <display-name>Sony HD ³</display-name>
  </channel>
  <channel id="FX HD ³">
    <display-name>FX HD ³</display-name>
  </channel>
  <channel id="AXN HD ³">
    <display-name>AXN HD ³</display-name>
  </channel>
  <channel id="Tnt novelas HD">
    <display-name>Tnt novelas HD</display-name>
  </channel>
  <channel id="Comedy Central HD">
    <display-name>Comedy Central HD</display-name>
  </channel>
  <channel id="AE HD">
    <display-name>AE HD</display-name>
  </channel>
  <channel id="ID HD ³">
    <display-name>ID HD ³</display-name>
  </channel>
  <channel id="Syfy HD">
    <display-name>Syfy HD</display-name>
  </channel>
  <channel id="Lifetime HD">
    <display-name>Lifetime HD</display-name>
  </channel>
  <channel id="TNT SÉRIES HD">
    <display-name>TNT SÉRIES HD</display-name>
  </channel>
  <channel id="Cinecanal HD">
    <display-name>Cinecanal HD</display-name>
  </channel>
  <channel id="AMC HD">
    <display-name>AMC HD</display-name>
  </channel>
  <channel id="Eurochannel HD">
    <display-name>Eurochannel HD</display-name>
  </channel>
  <channel id="FilmArts HD">
    <display-name>FilmArts HD</display-name>
  </channel>
  <channel id="Canal Brasil HD ³">
    <display-name>Canal Brasil HD ³</display-name>
  </channel>
  <channel id="TNT HD ³">
    <display-name>TNT HD ³</display-name>
  </channel>
  <channel id="Megapix HD ³">
    <display-name>Megapix HD ³</display-name>
  </channel>
  <channel id="Space HD ³">
    <display-name>Space HD ³</display-name>
  </channel>
  <channel id="Cinemax HD ³">
    <display-name>Cinemax HD ³</display-name>
  </channel>
  <channel id="Prime Box Brazil HD ³">
    <display-name>Prime Box Brazil HD ³</display-name>
  </channel>
  <channel id="Studio Universal HD">
    <display-name>Studio Universal HD</display-name>
  </channel>
  <channel id="Paramount Network HD">
    <display-name>Paramount Network HD</display-name>
  </channel>
  <channel id="Telecine Premium HD ³">
    <display-name>Telecine Premium HD ³</display-name>
  </channel>
  <channel id="Telecine Action HD ³">
    <display-name>Telecine Action HD ³</display-name>
  </channel>
  <channel id="Telecine Touch HD ³">
    <display-name>Telecine Touch HD ³</display-name>
  </channel>
  <channel id="Telecine Fun HD ³">
    <display-name>Telecine Fun HD ³</display-name>
  </channel>
  <channel id="Telecine Pipoca HD ³">
    <display-name>Telecine Pipoca HD ³</display-name>
  </channel>
  <channel id="Telecine Cult HD ³">
    <display-name>Telecine Cult HD ³</display-name>
  </channel>
  <channel id="HBO HD ³">
    <display-name>HBO HD ³</display-name>
  </channel>
  <channel id="HBO HD 2 ³">
    <display-name>HBO HD 2 ³</display-name>
  </channel>
  <channel id="HBO + HD">
    <display-name>HBO + HD</display-name>
  </channel>
  <channel id="HBO Family HD ³">
    <display-name>HBO Family HD ³</display-name>
  </channel>
  <channel id="HBO Signature HD ³">
    <display-name>HBO Signature HD ³</display-name>
  </channel>
  <channel id="HBO POP HD">
    <display-name>HBO POP HD</display-name>
  </channel>
  <channel id="HBO MUNDI HD">
    <display-name>HBO MUNDI HD</display-name>
  </channel>
  <channel id="HBO Xtreme HD">
    <display-name>HBO Xtreme HD</display-name>
  </channel>
  <channel id="Agro Mais HD">
    <display-name>Agro Mais HD</display-name>
  </channel>
  <channel id="TV Pai Eterno HD">
    <display-name>TV Pai Eterno HD</display-name>
  </channel>
  <channel id="Rede Vida HD">
    <display-name>Rede Vida HD</display-name>
  </channel>
  <channel id="TV Aparecida (espelho)">
    <display-name>TV Aparecida (espelho)</display-name>
  </channel>
  <channel id="Canal do Boi HD">
    <display-name>Canal do Boi HD</display-name>
  </channel>
  <channel id="France 24 HD">
    <display-name>France 24 HD</display-name>
  </channel>
  <channel id="CONMEBOL TV 4 HD">
    <display-name>CONMEBOL TV 4 HD</display-name>
  </channel>
  <channel id="Premiere Clubes HD">
    <display-name>Premiere Clubes HD</display-name>
  </channel>
  <channel id="Premiere HD 2">
    <display-name>Premiere HD 2</display-name>
  </channel>
  <channel id="PREMIERE HD 3 ³">
    <display-name>PREMIERE HD 3 ³</display-name>
  </channel>
  <channel id="PREMIERE HD 4 ³">
    <display-name>PREMIERE HD 4 ³</display-name>
  </channel>
  <channel id="PREMIERE HD 5 ³">
    <display-name>PREMIERE HD 5 ³</display-name>
  </channel>
  <channel id="Premiere HD 6">
    <display-name>Premiere HD 6</display-name>
  </channel>
  <channel id="Premiere HD 7">
    <display-name>Premiere HD 7</display-name>
  </channel>
  <channel id="Combate HD">
    <display-name>Combate HD</display-name>
  </channel>
  <channel id="Playboy HD">
    <display-name>Playboy HD</display-name>
  </channel>
  <programme start="20260526000000 -0300" stop="20260526020000 -0300" channel="Premiere 2">
    <title>Dia 31/05 - São Bernardo FC x Novorizontino</title>
  </programme>
  <programme start="20260526020000 -0300" stop="20260526040000 -0300" channel="Premiere 2">
    <title>Dia 31/05 - São Bernardo FC x Novorizontino</title>
  </programme>
  <programme start="20260526040000 -0300" stop="20260526060000 -0300" channel="Premiere 2">
    <title>Dia 31/05 - São Bernardo FC x Novorizontino</title>
  </programme>
  <programme start="20260526060000 -0300" stop="20260526080000 -0300" channel="Premiere 2">
    <title>Dia 31/05 - São Bernardo FC x Novorizontino</title>
  </programme>
  <programme start="20260526080000 -0300" stop="20260526100000 -0300" channel="Premiere 2">
    <title>Dia 31/05 - São Bernardo FC x Novorizontino</title>
  </programme>
  <programme start="20260526100000 -0300" stop="20260526120000 -0300" channel="Premiere 2">
    <title>Dia 31/05 - São Bernardo FC x Novorizontino</title>
  </programme>
  <programme start="20260526120000 -0300" stop="20260526140000 -0300" channel="Premiere 2">
    <title>Dia 31/05 - São Bernardo FC x Novorizontino</title>
  </programme>
  <programme start="20260526140000 -0300" stop="20260526160000 -0300" channel="Premiere 2">
    <title>Dia 31/05 - São Bernardo FC x Novorizontino</title>
  </programme>
  <programme start="20260526160000 -0300" stop="20260526180000 -0300" channel="Premiere 2">
    <title>Dia 31/05 - São Bernardo FC x Novorizontino</title>
  </programme>
  <programme start="20260526180000 -0300" stop="20260526200000 -0300" channel="Premiere 2">
    <title>Dia 31/05 - São Bernardo FC x Novorizontino</title>
  </programme>
  <programme start="20260526200000 -0300" stop="20260526220000 -0300" channel="Premiere 2">
    <title>Dia 31/05 - São Bernardo FC x Novorizontino</title>
  </programme>
  <programme start="20260526220000 -0300" stop="20260527000000 -0300" channel="Premiere 2">
    <title>Dia 31/05 - São Bernardo FC x Novorizontino</title>
  </programme>
  <programme start="20260526000000 -0300" stop="20260526003000 -0300" channel="Premiere Clubes">
    <title>VT - Santos x Coritiba</title>
  </programme>
  <programme start="20260526003000 -0300" stop="20260526010000 -0300" channel="Premiere Clubes">
    <title>VT - Bahia x Grêmio</title>
  </programme>
  <programme start="20260526010000 -0300" stop="20260526013000 -0300" channel="Premiere Clubes">
    <title>VT - Botafogo x Corinthians</title>
  </programme>
  <programme start="20260526013000 -0300" stop="20260526020000 -0300" channel="Premiere Clubes">
    <title>VT - Bragantino x Vitória</title>
  </programme>
  <programme start="20260526020000 -0300" stop="20260526023000 -0300" channel="Premiere Clubes">
    <title>VT - Chapecoense x Remo</title>
  </programme>
  <programme start="20260526023000 -0300" stop="20260526030000 -0300" channel="Premiere Clubes">
    <title>VT - Botafogo x Corinthians</title>
  </programme>
  <programme start="20260526030000 -0300" stop="20260526033000 -0300" channel="Premiere Clubes">
    <title>VT - Fluminense x São Paulo</title>
  </programme>
  <programme start="20260526033000 -0300" stop="20260526040000 -0300" channel="Premiere Clubes">
    <title>VT - Botafogo x Corinthians</title>
  </programme>
  <programme start="20260526040000 -0300" stop="20260526043000 -0300" channel="Premiere Clubes">
    <title>VT - Atlético-MG x Mirassol</title>
  </programme>
  <programme start="20260526043000 -0300" stop="20260526050000 -0300" channel="Premiere Clubes">
    <title>VT - Botafogo x Corinthians</title>
  </programme>
  <programme start="20260526050000 -0300" stop="20260526053000 -0300" channel="Premiere Clubes">
    <title>VT - Bragantino x Vitória</title>
  </programme>
  <programme start="20260526053000 -0300" stop="20260526060000 -0300" channel="Premiere Clubes">
    <title>VT - Santos x Coritiba</title>
  </programme>
  <programme start="20260526060000 -0300" stop="20260526063000 -0300" channel="Premiere Clubes">
    <title>VT - Chapecoense x Remo</title>
  </programme>
  <programme start="20260526063000 -0300" stop="20260526070000 -0300" channel="Premiere Clubes">
    <title>VT - Palmeiras x Cruzeiro</title>
  </programme>
  <programme start="20260526070000 -0300" stop="20260526073000 -0300" channel="Premiere Clubes">
    <title>VT - Bahia x Grêmio</title>
  </programme>
  <programme start="20260526073000 -0300" stop="20260526083000 -0300" channel="Premiere Clubes">
    <title>Giro Da Rodada - Brasileirão - 16ª Rodada</title>
  </programme>
  <programme start="20260526083000 -0300" stop="20260526090000 -0300" channel="Premiere Clubes">
    <title>VT - Atlético-MG x Mirassol</title>
  </programme>
  <programme start="20260526090000 -0300" stop="20260526093000 -0300" channel="Premiere Clubes">
    <title>VT - Fluminense x São Paulo</title>
  </programme>
  <programme start="20260526093000 -0300" stop="20260526100000 -0300" channel="Premiere Clubes">
    <title>VT - Palmeiras x Cruzeiro</title>
  </programme>
  <programme start="20260526100000 -0300" stop="20260526103000 -0300" channel="Premiere Clubes">
    <title>VT - Santos x Coritiba</title>
  </programme>
  <programme start="20260526103000 -0300" stop="20260526110000 -0300" channel="Premiere Clubes">
    <title>VT - Bahia x Grêmio</title>
  </programme>
  <programme start="20260526110000 -0300" stop="20260526113000 -0300" channel="Premiere Clubes">
    <title>VT - Botafogo x Corinthians</title>
  </programme>
  <programme start="20260526113000 -0300" stop="20260526120000 -0300" channel="Premiere Clubes">
    <title>VT - Bragantino x Vitória</title>
  </programme>
  <programme start="20260526120000 -0300" stop="20260526123000 -0300" channel="Premiere Clubes">
    <title>VT - Chapecoense x Remo</title>
  </programme>
  <programme start="20260526123000 -0300" stop="20260526130000 -0300" channel="Premiere Clubes">
    <title>VT - Bahia x Grêmio</title>
  </programme>
  <programme start="20260526130000 -0300" stop="20260526133000 -0300" channel="Premiere Clubes">
    <title>VT - Fluminense x São Paulo</title>
  </programme>
  <programme start="20260526133000 -0300" stop="20260526140000 -0300" channel="Premiere Clubes">
    <title>VT - Botafogo x Corinthians</title>
  </programme>
  <programme start="20260526140000 -0300" stop="20260526143000 -0300" channel="Premiere Clubes">
    <title>VT - Bragantino x Vitória</title>
  </programme>
  <programme start="20260526143000 -0300" stop="20260526150000 -0300" channel="Premiere Clubes">
    <title>VT - Atlético-MG x Mirassol</title>
  </programme>
  <programme start="20260526150000 -0300" stop="20260526153000 -0300" channel="Premiere Clubes">
    <title>VT - Bragantino x Vitória</title>
  </programme>
  <programme start="20260526153000 -0300" stop="20260526160000 -0300" channel="Premiere Clubes">
    <title>VT - Santos x Coritiba</title>
  </programme>
  <programme start="20260526160000 -0300" stop="20260526163000 -0300" channel="Premiere Clubes">
    <title>VT - Chapecoense x Remo</title>
  </programme>
  <programme start="20260526163000 -0300" stop="20260526170000 -0300" channel="Premiere Clubes">
    <title>VT - Palmeiras x Cruzeiro</title>
  </programme>
  <programme start="20260526170000 -0300" stop="20260526173000 -0300" channel="Premiere Clubes">
    <title>VT - Bahia x Grêmio</title>
  </programme>
  <programme start="20260526173000 -0300" stop="20260526183000 -0300" channel="Premiere Clubes">
    <title>VT - Grêmio x Internacional</title>
  </programme>
  <programme start="20260526183000 -0300" stop="20260526193000 -0300" channel="Premiere Clubes">
    <title>VT - Fluminense x São Paulo</title>
  </programme>
  <programme start="20260526193000 -0300" stop="20260526200000 -0300" channel="Premiere Clubes">
    <title>VT - Atlético-MG x Mirassol</title>
  </programme>
  <programme start="20260526200000 -0300" stop="20260526203000 -0300" channel="Premiere Clubes">
    <title>VT - Fluminense x São Paulo</title>
  </programme>
  <programme start="20260526203000 -0300" stop="20260526210000 -0300" channel="Premiere Clubes">
    <title>VT - Palmeiras x Cruzeiro</title>
  </programme>
  <programme start="20260526210000 -0300" stop="20260526213000 -0300" channel="Premiere Clubes">
    <title>VT - Santos x Coritiba</title>
  </programme>
  <programme start="20260526213000 -0300" stop="20260526220000 -0300" channel="Premiere Clubes">
    <title>VT - Bahia x Grêmio</title>
  </programme>
  <programme start="20260526220000 -0300" stop="20260526223000 -0300" channel="Premiere Clubes">
    <title>VT - Botafogo x Corinthians</title>
  </programme>
  <programme start="20260526223000 -0300" stop="20260526230000 -0300" channel="Premiere Clubes">
    <title>VT - Bragantino x Vitória</title>
  </programme>
  <programme start="20260526230000 -0300" stop="20260526233000 -0300" channel="Premiere Clubes">
    <title>VT - Chapecoense x Remo</title>
  </programme>
  <programme start="20260526233000 -0300" stop="20260527000000 -0300" channel="Premiere Clubes">
    <title>VT - Athletico-PR x Flamengo</title>
  </programme>
</tv>
